emoticon_fix/__init__.py
emoticon_fix/emoticon_fix.py
emoticon_fix/__pycache__/__init__.cpython-38.pyc
emoticon_fix/__pycache__/emoticon_fix.cpython-38.pyc
emoticon_fix-0.3.0.dist-info/licenses/LICENSE
emoticon_fix-0.3.0.dist-info/METADATA
emoticon_fix-0.3.0.dist-info/WHEEL
emoticon_fix-0.3.0.dist-info/top_level.txt
emoticon_fix-0.3.0.dist-info/RECORD
