Metadata-Version: 2.4
Name: emoticon-fix
Version: 0.3.0
Summary: A lightweight and efficient library for transforming emoticons into their semantic meanings with sentiment analysis capabilities
Home-page: https://github.com/xga0/emoticon_fix
Author: Sean Gao
Author-email: Sean Gao <seangaoxy@gmail.com>
License: MIT License
Project-URL: Homepage, https://github.com/xga0/emoticon_fix
Project-URL: Repository, https://github.com/xga0/emoticon_fix
Project-URL: Documentation, https://github.com/xga0/emoticon_fix#readme
Project-URL: Bug Tracker, https://github.com/xga0/emoticon_fix/issues
Classifier: Development Status :: 4 - Beta
Classifier: Intended Audience :: Science/Research
Classifier: Intended Audience :: Developers
Classifier: Topic :: Text Processing :: Linguistic
Classifier: Programming Language :: Python :: 3
Classifier: Programming Language :: Python :: 3.6
Classifier: Programming Language :: Python :: 3.7
Classifier: Programming Language :: Python :: 3.8
Classifier: Programming Language :: Python :: 3.9
Classifier: Programming Language :: Python :: 3.10
Classifier: Programming Language :: Python :: 3.11
Classifier: Programming Language :: Python :: 3.12
Classifier: License :: OSI Approved :: MIT License
Classifier: Operating System :: OS Independent
Classifier: Natural Language :: English
Requires-Python: >=3.6
License-File: LICENSE
Provides-Extra: dev
Requires-Dist: pytest>=6.0; extra == "dev"
Requires-Dist: pytest-cov>=2.0; extra == "dev"
Requires-Dist: black>=21.0; extra == "dev"
Requires-Dist: mypy>=0.800; extra == "dev"
Requires-Dist: flake8>=3.9; extra == "dev"
Requires-Dist: build>=0.7.0; extra == "dev"
Requires-Dist: twine>=4.0.0; extra == "dev"
Dynamic: author
Dynamic: home-page
Dynamic: license-file
Dynamic: requires-python
